{"resource-aws-iot-logging-options": "<h1 id=\"resource-aws_iot_logging_options\">Resource: aws_iot_logging_options</h1><p>Provides a resource to manage <a href=\"https://docs.aws.amazon.com/iot/latest/developerguide/configure-logging.html#configure-logging-console\">default logging options</a>.</p>", "example-usage": "<h2 id=\"example-usage\">Example Usage</h2><p><code>terraformresource \"aws_iot_logging_options\" \"example\" {  default_log_level = \"WARN\"  role_arn          = aws_iam_role.example.arn}</code></p>", "argument-reference": "<h2 id=\"argument-reference\">Argument Reference</h2><ul><li><code>default_log_level</code> - (Optional) The default logging level. Valid Values: <code>\"DEBUG\"</code>, <code>\"INFO\"</code>, <code>\"ERROR\"</code>, <code>\"WARN\"</code>, <code>\"DISABLED\"</code>.</li><li><code>disable_all_logs</code> - (Optional) If <code>true</code> all logs are disabled. The default is <code>false</code>.</li><li><code>role_arn</code> - (Required) The ARN of the role that allows IoT to write to Cloudwatch logs.</li></ul>", "attribute-reference": "<h2 id=\"attribute-reference\">Attribute Reference</h2><p>This resource exports no additional attributes.</p>", "description": "<h1 id=\"resource-aws_iot_logging_options\">Resource: aws_iot_logging_options</h1><p>Provides a resource to manage <a href=\"https://docs.aws.amazon.com/iot/latest/developerguide/configure-logging.html#configure-logging-console\">default logging options</a>.</p>"}